Metadata-Version: 1.1
Name: dtool-smb
Version: 0.1.0
Summary: Add SMB (Server Message Block) dataset support to dtool
Home-page: https://github.com/IMTEK-Simulation/dtool-smb
Author: Lars Pastewka
Author-email: lars.pastewka@imtek.uni-freiburg.de
License: MIT
Download-URL: https://github.com/IMTEK-Simulation/dtool-smb/tarball/0.1.0
Platform: UNKNOWN
